jai_STT/__init__.py
jai_stt-0.1.dist-info/METADATA
jai_stt-0.1.dist-info/WHEEL
jai_stt-0.1.dist-info/top_level.txt
jai_stt-0.1.dist-info/RECORD
