Metadata-Version: 2.4
Name: jai-STT
Version: 0.1
Summary: Speech to text by Jai
Author: Jai Yadav
Author-email: dragon4u4u4@gmail.com
Requires-Dist: selenium
Requires-Dist: webdriver-manager
Dynamic: author
Dynamic: author-email
Dynamic: requires-dist
Dynamic: summary
